<?xml version="1.0" encoding="UTF-8"?>
<MetaDataObject xmlns="http://v8.1c.ru/8.3/MDClasses" xmlns:app="http://v8.1c.ru/8.2/managed-application/core" xmlns:cfg="http://v8.1c.ru/8.1/data/enterprise/current-config" xmlns:cmi="http://v8.1c.ru/8.2/managed-application/cmi" xmlns:ent="http://v8.1c.ru/8.1/data/enterprise" xmlns:lf="http://v8.1c.ru/8.2/managed-application/logform" xmlns:style="http://v8.1c.ru/8.1/data/ui/style" xmlns:sys="http://v8.1c.ru/8.1/data/ui/fonts/system" xmlns:v8="http://v8.1c.ru/8.1/data/core" xmlns:v8ui="http://v8.1c.ru/8.1/data/ui" xmlns:web="http://v8.1c.ru/8.1/data/ui/colors/web" xmlns:win="http://v8.1c.ru/8.1/data/ui/colors/windows" xmlns:xen="http://v8.1c.ru/8.3/xcf/enums" xmlns:xpr="http://v8.1c.ru/8.3/xcf/predef" xmlns:xr="http://v8.1c.ru/8.3/xcf/readable" xmlns:xs="http://www.w3.org/2001/XMLSchema" xmlns:xsi="http://www.w3.org/2001/XMLSchema-instance" version="2.9">
	<Constant uuid="49c861aa-8e7f-430d-bc20-a009c088e633">
		<InternalInfo>
			<xr:GeneratedType name="ConstantManager.воКоличествоПотоковОбработкиПриоритетов" category="Manager">
				<xr:TypeId>a55b210b-0224-4a82-8f69-28d2d33abfc3</xr:TypeId>
				<xr:ValueId>0a9efae7-e589-4c88-bb90-e8713b4eca26</xr:ValueId>
			</xr:GeneratedType>
			<xr:GeneratedType name="ConstantValueManager.воКоличествоПотоковОбработкиПриоритетов" category="ValueManager">
				<xr:TypeId>f5daa141-476c-4a13-9433-47c8a2dea9e0</xr:TypeId>
				<xr:ValueId>0a72a4aa-4710-4c7b-a7ed-ac5bf461b882</xr:ValueId>
			</xr:GeneratedType>
			<xr:GeneratedType name="ConstantValueKey.воКоличествоПотоковОбработкиПриоритетов" category="ValueKey">
				<xr:TypeId>d9dbf9f9-ee4a-43af-b96b-449883999f30</xr:TypeId>
				<xr:ValueId>cd482b13-3e55-414b-abfa-a833d0da53ee</xr:ValueId>
			</xr:GeneratedType>
		</InternalInfo>
		<Properties>
			<Name>воКоличествоПотоковОбработкиПриоритетов</Name>
			<Synonym>
				<v8:item>
					<v8:lang>ru</v8:lang>
					<v8:content>Количество потоков обработки приоритетов</v8:content>
				</v8:item>
			</Synonym>
			<Comment/>
			<Type>
				<v8:Type>xs:decimal</v8:Type>
				<v8:NumberQualifiers>
					<v8:Digits>2</v8:Digits>
					<v8:FractionDigits>0</v8:FractionDigits>
					<v8:AllowedSign>Nonnegative</v8:AllowedSign>
				</v8:NumberQualifiers>
			</Type>
			<UseStandardCommands>true</UseStandardCommands>
			<DefaultForm>CommonForm.воФормаКонстант</DefaultForm>
			<ExtendedPresentation/>
			<Explanation/>
			<PasswordMode>false</PasswordMode>
			<Format/>
			<EditFormat/>
			<ToolTip/>
			<MarkNegatives>false</MarkNegatives>
			<Mask/>
			<MultiLine>false</MultiLine>
			<ExtendedEdit>false</ExtendedEdit>
			<MinValue xsi:nil="true"/>
			<MaxValue xsi:nil="true"/>
			<FillChecking>DontCheck</FillChecking>
			<ChoiceFoldersAndItems>Items</ChoiceFoldersAndItems>
			<ChoiceParameterLinks/>
			<ChoiceParameters/>
			<QuickChoice>Auto</QuickChoice>
			<ChoiceForm/>
			<LinkByType/>
			<ChoiceHistoryOnInput>Auto</ChoiceHistoryOnInput>
			<DataLockControlMode>Managed</DataLockControlMode>
			<DataHistory>DontUse</DataHistory>
			<UpdateDataHistoryImmediatelyAfterWrite>false</UpdateDataHistoryImmediatelyAfterWrite>
			<ExecuteAfterWriteDataHistoryVersionProcessing>false</ExecuteAfterWriteDataHistoryVersionProcessing>
		</Properties>
	</Constant>
</MetaDataObject>